setup.py
Masheen/Masheen.py
Masheen/__init__.py
Masheen/__main__.py
Masheen.egg-info/PKG-INFO
Masheen.egg-info/SOURCES.txt
Masheen.egg-info/dependency_links.txt
Masheen.egg-info/not-zip-safe
Masheen.egg-info/top_level.txt
masheen.egg-info/PKG-INFO
masheen.egg-info/SOURCES.txt
masheen.egg-info/dependency_links.txt
masheen.egg-info/not-zip-safe
masheen.egg-info/top_level.txt