Metadata-Version: 1.0
Name: Masheen
Version: 0.2
Summary: A Masheen for brainfuck.
Home-page: http://github.com/micha2718l/Masheen
Author: micha2718l
Author-email: micha2718l@gmail.com
License: MIT
Platform: UNKNOWN
